setup.py
toka.egg-info/PKG-INFO
toka.egg-info/SOURCES.txt
toka.egg-info/dependency_links.txt
toka.egg-info/entry_points.txt
toka.egg-info/top_level.txt
tokapy/__init__.py
tokapy/toka.py
tokapy/lib/gitignore
tokapy/lib/license
tokapy/lib/webpack
tokapy/lib/gitignore/Actionscript.gitignore
tokapy/lib/gitignore/Ada.gitignore
tokapy/lib/gitignore/Agda.gitignore
tokapy/lib/gitignore/Android.gitignore
tokapy/lib/gitignore/AppEngine.gitignore
tokapy/lib/gitignore/AppceleratorTitanium.gitignore
tokapy/lib/gitignore/ArchLinuxPackages.gitignore
tokapy/lib/gitignore/Autotools.gitignore
tokapy/lib/gitignore/C++.gitignore
tokapy/lib/gitignore/C.gitignore
tokapy/lib/gitignore/CFWheels.gitignore
tokapy/lib/gitignore/CMake.gitignore
tokapy/lib/gitignore/CakePHP.gitignore
tokapy/lib/gitignore/ChefCookbook.gitignore
tokapy/lib/gitignore/Clojure.gitignore
tokapy/lib/gitignore/CodeIgniter.gitignore
tokapy/lib/gitignore/CommonLisp.gitignore
tokapy/lib/gitignore/Composer.gitignore
tokapy/lib/gitignore/Concrete5.gitignore
tokapy/lib/gitignore/Coq.gitignore
tokapy/lib/gitignore/CraftCMS.gitignore
tokapy/lib/gitignore/DM.gitignore
tokapy/lib/gitignore/Dart.gitignore
tokapy/lib/gitignore/Default.gitignore
tokapy/lib/gitignore/Delphi.gitignore
tokapy/lib/gitignore/Drupal.gitignore
tokapy/lib/gitignore/EPiServer.gitignore
tokapy/lib/gitignore/Eagle.gitignore
tokapy/lib/gitignore/Elisp.gitignore
tokapy/lib/gitignore/Elixir.gitignore
tokapy/lib/gitignore/Erlang.gitignore
tokapy/lib/gitignore/ExpressionEngine.gitignore
tokapy/lib/gitignore/ExtJs.gitignore
tokapy/lib/gitignore/Fancy.gitignore
tokapy/lib/gitignore/Finale.gitignore
tokapy/lib/gitignore/ForceDotCom.gitignore
tokapy/lib/gitignore/Fortran.gitignore
tokapy/lib/gitignore/FuelPHP.gitignore
tokapy/lib/gitignore/GWT.gitignore
tokapy/lib/gitignore/Gcov.gitignore
tokapy/lib/gitignore/GitBook.gitignore
tokapy/lib/gitignore/Go.gitignore
tokapy/lib/gitignore/Gradle.gitignore
tokapy/lib/gitignore/Grails.gitignore
tokapy/lib/gitignore/Haskell.gitignore
tokapy/lib/gitignore/IGORPro.gitignore
tokapy/lib/gitignore/Idris.gitignore
tokapy/lib/gitignore/Java.gitignore
